monochrome_dionny/__init__.py
monochrome_dionny/module.py
monochrome_dionny-0.0.3.dist-info/METADATA
monochrome_dionny-0.0.3.dist-info/WHEEL
monochrome_dionny-0.0.3.dist-info/top_level.txt
monochrome_dionny-0.0.3.dist-info/RECORD
