Metadata-Version: 2.2
Name: monochrome_dionny
Version: 0.0.3
Summary: Transformar as cores de uma imagem em tons de cinza ou binarizadas em preto e branco
Author: Dionny
Requires-Dist: numpy
Requires-Dist: pillow
Dynamic: author
Dynamic: description
Dynamic: description-content-type
Dynamic: requires-dist
Dynamic: summary
